autobr/__init__.py
autobr/autobr.py
autobr/baidu.py
autobr/browser.py
autobr/fetch_list.py
autobr/fetch_text.py
autobr/__pycache__/__init__.cpython-36.pyc
autobr/__pycache__/__init__.cpython-39.pyc
autobr/__pycache__/autobr.cpython-36.pyc
autobr/__pycache__/autobr.cpython-39.pyc
autobr/__pycache__/baidu.cpython-36.pyc
autobr/__pycache__/baidu.cpython-39.pyc
autobr/__pycache__/browser.cpython-36.pyc
autobr/__pycache__/browser.cpython-39.pyc
autobr/__pycache__/fetch_list.cpython-36.pyc
autobr/__pycache__/fetch_text.cpython-36.pyc
autobr-0.0.4.dist-info/LICENSE
autobr-0.0.4.dist-info/METADATA
autobr-0.0.4.dist-info/WHEEL
autobr-0.0.4.dist-info/top_level.txt
autobr-0.0.4.dist-info/RECORD
